RsCmwLteSig/RsCmwLteSig.py
RsCmwLteSig/__init__.py
RsCmwLteSig/enums.py
RsCmwLteSig/repcap.py
RsCmwLteSig/CustomFiles/__init__.py
RsCmwLteSig/CustomFiles/events.py
RsCmwLteSig/CustomFiles/reliability.py
RsCmwLteSig/CustomFiles/utilities.py
RsCmwLteSig/Implementations/__init__.py
RsCmwLteSig/Implementations/A/State.py
RsCmwLteSig/Implementations/A/__init__.py
RsCmwLteSig/Implementations/B/State.py
RsCmwLteSig/Implementations/B/__init__.py
RsCmwLteSig/Implementations/Call/A.py
RsCmwLteSig/Implementations/Call/B.py
RsCmwLteSig/Implementations/Call/Pswitched.py
RsCmwLteSig/Implementations/Call/__init__.py
RsCmwLteSig/Implementations/Call/Scc/Action.py
RsCmwLteSig/Implementations/Call/Scc/__init__.py
RsCmwLteSig/Implementations/Catalog/Connection.py
RsCmwLteSig/Implementations/Catalog/__init__.py
RsCmwLteSig/Implementations/Clean/EeLog.py
RsCmwLteSig/Implementations/Clean/Elog.py
RsCmwLteSig/Implementations/Clean/__init__.py
RsCmwLteSig/Implementations/Clean/Sms/__init__.py
RsCmwLteSig/Implementations/Clean/Sms/Incoming/__init__.py
RsCmwLteSig/Implementations/Clean/Sms/Incoming/Info/Mtext.py
RsCmwLteSig/Implementations/Clean/Sms/Incoming/Info/__init__.py
RsCmwLteSig/Implementations/Configure/Caggregation.py
RsCmwLteSig/Implementations/Configure/EeLog.py
RsCmwLteSig/Implementations/Configure/Throughput.py
RsCmwLteSig/Implementations/Configure/__init__.py
RsCmwLteSig/Implementations/Configure/A/__init__.py
RsCmwLteSig/Implementations/Configure/A/Scc/Enable.py
RsCmwLteSig/Implementations/Configure/A/Scc/__init__.py
RsCmwLteSig/Implementations/Configure/B/__init__.py
RsCmwLteSig/Implementations/Configure/B/Scc/Enable.py
RsCmwLteSig/Implementations/Configure/B/Scc/__init__.py
RsCmwLteSig/Implementations/Configure/Cbs/__init__.py
RsCmwLteSig/Implementations/Configure/Cbs/Message/DcScheme.py
RsCmwLteSig/Implementations/Configure/Cbs/Message/Etws.py
RsCmwLteSig/Implementations/Configure/Cbs/Message/File.py
RsCmwLteSig/Implementations/Configure/Cbs/Message/Language.py
RsCmwLteSig-4.0.20.dist-info/METADATA
RsCmwLteSig-4.0.20.dist-info/WHEEL
RsCmwLteSig-4.0.20.dist-info/top_level.txt
RsCmwLteSig-4.0.20.dist-info/RECORD
